xboxbattery/__init__.py
xboxbattery/connection.py
xboxbattery/device.py
xboxbattery/main.py
xboxbattery/menu.py
xboxbattery-0.2.0.dist-info/METADATA
xboxbattery-0.2.0.dist-info/WHEEL
xboxbattery-0.2.0.dist-info/entry_points.txt
xboxbattery-0.2.0.dist-info/RECORD
